[
    {
        "name": "Viaje orbital 🌎",
        "img": "https://cdn-icons.flaticon.com/png/512/3594/premium/3594229.png?token=exp=1647802112~hmac=e1bebc32fc3248d747199419c9e536a4",
        "price": 29990
    },
    {
        "name": "Viaje a la luna 🌙",
        "img": "https://cdn-icons.flaticon.com/png/512/3594/premium/3594160.png?token=exp=1647802797~hmac=dcbadc4fb0478b519ff26cf0199e6a1b",
        "price": 99990
    },
    {
        "name": "Viaje al sol 🌞 (solo de ida)",
        "img": "https://cdn-icons.flaticon.com/png/512/3594/premium/3594101.png?token=exp=1647802168~hmac=edf5963e57b0221c009107a55b3d0d1e",
        "price": 599990
    },
    {
        "name": "Viaje a Mercurio",
        "img": "https://cdn-icons.flaticon.com/png/512/3594/premium/3594191.png?token=exp=1647802528~hmac=a7039690e6b044fc07d8bf9e3b3dc0a3",
        "price": 159990
    },
    {
        "name": "Viaje a Venus",
        "img": "https://cdn-icons.flaticon.com/png/512/3594/premium/3594270.png?token=exp=1647802741~hmac=afc6a127d42aef1a6bc5cc55d257730b",
        "price": 129990
    },
    {
        "name": "Viaje a Marte",
        "img": "https://cdn-icons.flaticon.com/png/512/3594/premium/3594291.png?token=exp=1647802548~hmac=700c3b1283b8df09bb5d4aa5f4b6b94d",
        "price": 129990
    },
    {
        "name": "Viaje por el cinturon de asteroides",
        "img": "https://cdn-icons-png.flaticon.com/512/3594/3594080.png",
        "price": 179990
    },
    {
        "name": "Viaje orbital a Jupiter",
        "img": "https://cdn-icons-png.flaticon.com/512/3594/3594079.png",
        "price": 229990
    },
    {
        "name": "Viaje orbital a Saturno",
        "img": "https://cdn-icons-png.flaticon.com/512/3594/3594077.png",
        "price": 249990
    },
    {
        "name": "Viaje orbital a Urano",
        "img": "https://cdn-icons-png.flaticon.com/512/3594/3594083.png",
        "price": 299990
    },
    {
        "name": "Viaje orbital a Neptuno",
        "img": "https://cdn-icons-png.flaticon.com/512/3594/3594089.png",
        "price": 319990
    }
]